finmath/__init__.py
finmath/finmath.cpython-313-x86_64-linux-gnu.so
finmath/libfinmath_library.so
finmath-0.1.16.dist-info/METADATA
finmath-0.1.16.dist-info/WHEEL
finmath-0.1.16.dist-info/RECORD
finmath-0.1.16.dist-info/licenses/LICENSE
